{
  "id": "efb4b5b9-5b2f-493c-9652-1d104de45987",
  "prevId": "00000000-0000-0000-0000-000000000000",
  "version": "7",
  "dialect": "postgresql",
  "tables": {
    "public.catalog_entries": {
      "name": "catalog_entries",
      "schema": "",
      "columns": {
        "id": {
          "name": "id",
          "type": "text",
          "primaryKey": true,
          "notNull": true
        },
        "catalog_id": {
          "name": "catalog_id",
          "type": "text",
          "primaryKey": false,
          "notNull": true
        },
        "commercial_object_id": {
          "name": "commercial_object_id",
          "type": "text",
          "primaryKey": false,
          "notNull": true
        },
        "object_type": {
          "name": "object_type",
          "type": "text",
          "primaryKey": false,
          "notNull": true
        },
        "provider_id": {
          "name": "provider_id",
          "type": "text",
          "primaryKey": false,
          "notNull": true,
          "default": "''"
        },
        "object_id": {
          "name": "object_id",
          "type": "text",
          "primaryKey": false,
          "notNull": true,
          "default": "''"
        },
        "entry_status": {
          "name": "entry_status",
          "type": "entry_status",
          "typeSchema": "public",
          "primaryKey": false,
          "notNull": true,
          "default": "'pending_verification'"
        },
        "contract_match_status": {
          "name": "contract_match_status",
          "type": "text",
          "primaryKey": false,
          "notNull": true,
          "default": "'unchecked'"
        },
        "title": {
          "name": "title",
          "type": "text",
          "primaryKey": false,
          "notNull": true,
          "default": "''"
        },
        "summary": {
          "name": "summary",
          "type": "text",
          "primaryKey": false,
          "notNull": false
        },
        "brand": {
          "name": "brand",
          "type": "text",
          "primaryKey": false,
          "notNull": false
        },
        "category": {
          "name": "category",
          "type": "text",
          "primaryKey": false,
          "notNull": false
        },
        "currency": {
          "name": "currency",
          "type": "text",
          "primaryKey": false,
          "notNull": false
        },
        "availability_status": {
          "name": "availability_status",
          "type": "text",
          "primaryKey": false,
          "notNull": false
        },
        "search_text": {
          "name": "search_text",
          "type": "text",
          "primaryKey": false,
          "notNull": true,
          "default": "''"
        },
        "search_projection": {
          "name": "search_projection",
          "type": "jsonb",
          "primaryKey": false,
          "notNull": true,
          "default": "'{}'::jsonb"
        },
        "explain_projection": {
          "name": "explain_projection",
          "type": "jsonb",
          "primaryKey": false,
          "notNull": true,
          "default": "'{}'::jsonb"
        },
        "created_at": {
          "name": "created_at",
          "type": "timestamp with time zone",
          "primaryKey": false,
          "notNull": true,
          "default": "now()"
        },
        "updated_at": {
          "name": "updated_at",
          "type": "timestamp with time zone",
          "primaryKey": false,
          "notNull": true,
          "default": "now()"
        }
      },
      "indexes": {
        "catalog_entries_catalog_type_status_idx": {
          "name": "catalog_entries_catalog_type_status_idx",
          "columns": [
            {
              "expression": "catalog_id",
              "isExpression": false,
              "asc": true,
              "nulls": "last"
            },
            {
              "expression": "object_type",
              "isExpression": false,
              "asc": true,
              "nulls": "last"
            },
            {
              "expression": "entry_status",
              "isExpression": false,
              "asc": true,
              "nulls": "last"
            }
          ],
          "isUnique": false,
          "concurrently": false,
          "method": "btree",
          "with": {}
        },
        "catalog_entries_catalog_provider_status_idx": {
          "name": "catalog_entries_catalog_provider_status_idx",
          "columns": [
            {
              "expression": "catalog_id",
              "isExpression": false,
              "asc": true,
              "nulls": "last"
            },
            {
              "expression": "provider_id",
              "isExpression": false,
              "asc": true,
              "nulls": "last"
            },
            {
              "expression": "entry_status",
              "isExpression": false,
              "asc": true,
              "nulls": "last"
            }
          ],
          "isUnique": false,
          "concurrently": false,
          "method": "btree",
          "with": {}
        },
        "catalog_entries_catalog_category_status_idx": {
          "name": "catalog_entries_catalog_category_status_idx",
          "columns": [
            {
              "expression": "catalog_id",
              "isExpression": false,
              "asc": true,
              "nulls": "last"
            },
            {
              "expression": "category",
              "isExpression": false,
              "asc": true,
              "nulls": "last"
            },
            {
              "expression": "entry_status",
              "isExpression": false,
              "asc": true,
              "nulls": "last"
            }
          ],
          "isUnique": false,
          "concurrently": false,
          "method": "btree",
          "with": {}
        },
        "catalog_entries_catalog_brand_status_idx": {
          "name": "catalog_entries_catalog_brand_status_idx",
          "columns": [
            {
              "expression": "catalog_id",
              "isExpression": false,
              "asc": true,
              "nulls": "last"
            },
            {
              "expression": "brand",
              "isExpression": false,
              "asc": true,
              "nulls": "last"
            },
            {
              "expression": "entry_status",
              "isExpression": false,
              "asc": true,
              "nulls": "last"
            }
          ],
          "isUnique": false,
          "concurrently": false,
          "method": "btree",
          "with": {}
        },
        "catalog_entries_catalog_availability_status_idx": {
          "name": "catalog_entries_catalog_availability_status_idx",
          "columns": [
            {
              "expression": "catalog_id",
              "isExpression": false,
              "asc": true,
              "nulls": "last"
            },
            {
              "expression": "availability_status",
              "isExpression": false,
              "asc": true,
              "nulls": "last"
            },
            {
              "expression": "entry_status",
              "isExpression": false,
              "asc": true,
              "nulls": "last"
            }
          ],
          "isUnique": false,
          "concurrently": false,
          "method": "btree",
          "with": {}
        },
        "catalog_entries_commercial_object_unique": {
          "name": "catalog_entries_commercial_object_unique",
          "columns": [
            {
              "expression": "commercial_object_id",
              "isExpression": false,
              "asc": true,
              "nulls": "last"
            }
          ],
          "isUnique": true,
          "concurrently": false,
          "method": "btree",
          "with": {}
        }
      },
      "foreignKeys": {
        "catalog_entries_commercial_object_id_commercial_objects_id_fk": {
          "name": "catalog_entries_commercial_object_id_commercial_objects_id_fk",
          "tableFrom": "catalog_entries",
          "tableTo": "commercial_objects",
          "columnsFrom": [
            "commercial_object_id"
          ],
          "columnsTo": [
            "id"
          ],
          "onDelete": "cascade",
          "onUpdate": "no action"
        }
      },
      "compositePrimaryKeys": {},
      "uniqueConstraints": {},
      "policies": {},
      "checkConstraints": {},
      "isRLSEnabled": false
    },
    "public.catalog_profiles": {
      "name": "catalog_profiles",
      "schema": "",
      "columns": {
        "id": {
          "name": "id",
          "type": "text",
          "primaryKey": true,
          "notNull": true
        },
        "catalog_id": {
          "name": "catalog_id",
          "type": "text",
          "primaryKey": false,
          "notNull": true
        },
        "catalog_name": {
          "name": "catalog_name",
          "type": "text",
          "primaryKey": false,
          "notNull": true
        },
        "manifest": {
          "name": "manifest",
          "type": "jsonb",
          "primaryKey": false,
          "notNull": true
        },
        "created_at": {
          "name": "created_at",
          "type": "timestamp with time zone",
          "primaryKey": false,
          "notNull": true,
          "default": "now()"
        },
        "updated_at": {
          "name": "updated_at",
          "type": "timestamp with time zone",
          "primaryKey": false,
          "notNull": true,
          "default": "now()"
        }
      },
      "indexes": {
        "catalog_profiles_catalog_id_unique": {
          "name": "catalog_profiles_catalog_id_unique",
          "columns": [
            {
              "expression": "catalog_id",
              "isExpression": false,
              "asc": true,
              "nulls": "last"
            }
          ],
          "isUnique": true,
          "concurrently": false,
          "method": "btree",
          "with": {}
        }
      },
      "foreignKeys": {},
      "compositePrimaryKeys": {},
      "uniqueConstraints": {},
      "policies": {},
      "checkConstraints": {},
      "isRLSEnabled": false
    },
    "public.catalog_search_documents": {
      "name": "catalog_search_documents",
      "schema": "",
      "columns": {
        "id": {
          "name": "id",
          "type": "text",
          "primaryKey": true,
          "notNull": true
        },
        "catalog_id": {
          "name": "catalog_id",
          "type": "text",
          "primaryKey": false,
          "notNull": true
        },
        "catalog_entry_id": {
          "name": "catalog_entry_id",
          "type": "text",
          "primaryKey": false,
          "notNull": true
        },
        "commercial_object_id": {
          "name": "commercial_object_id",
          "type": "text",
          "primaryKey": false,
          "notNull": true
        },
        "provider_id": {
          "name": "provider_id",
          "type": "text",
          "primaryKey": false,
          "notNull": true,
          "default": "''"
        },
        "object_id": {
          "name": "object_id",
          "type": "text",
          "primaryKey": false,
          "notNull": true,
          "default": "''"
        },
        "object_type": {
          "name": "object_type",
          "type": "text",
          "primaryKey": false,
          "notNull": true
        },
        "document_status": {
          "name": "document_status",
          "type": "catalog_search_document_status",
          "typeSchema": "public",
          "primaryKey": false,
          "notNull": true,
          "default": "'pending'"
        },
        "title": {
          "name": "title",
          "type": "text",
          "primaryKey": false,
          "notNull": true,
          "default": "''"
        },
        "normalized_title": {
          "name": "normalized_title",
          "type": "text",
          "primaryKey": false,
          "notNull": true,
          "default": "''"
        },
        "summary": {
          "name": "summary",
          "type": "text",
          "primaryKey": false,
          "notNull": false
        },
        "brand": {
          "name": "brand",
          "type": "text",
          "primaryKey": false,
          "notNull": false
        },
        "normalized_brand": {
          "name": "normalized_brand",
          "type": "text",
          "primaryKey": false,
          "notNull": true,
          "default": "''"
        },
        "category": {
          "name": "category",
          "type": "text",
          "primaryKey": false,
          "notNull": false
        },
        "normalized_category": {
          "name": "normalized_category",
          "type": "text",
          "primaryKey": false,
          "notNull": true,
          "default": "''"
        },
        "sku": {
          "name": "sku",
          "type": "text",
          "primaryKey": false,
          "notNull": false
        },
        "normalized_sku": {
          "name": "normalized_sku",
          "type": "text",
          "primaryKey": false,
          "notNull": true,
          "default": "''"
        },
        "currency": {
          "name": "currency",
          "type": "text",
          "primaryKey": false,
          "notNull": false
        },
        "availability_status": {
          "name": "availability_status",
          "type": "text",
          "primaryKey": false,
          "notNull": false
        },
        "amount": {
          "name": "amount",
          "type": "double precision",
          "primaryKey": false,
          "notNull": false
        },
        "list_amount": {
          "name": "list_amount",
          "type": "double precision",
          "primaryKey": false,
          "notNull": false
        },
        "has_image": {
          "name": "has_image",
          "type": "boolean",
          "primaryKey": false,
          "notNull": true,
          "default": false
        },
        "has_product_url": {
          "name": "has_product_url",
          "type": "boolean",
          "primaryKey": false,
          "notNull": true,
          "default": false
        },
        "discount_present": {
          "name": "discount_present",
          "type": "boolean",
          "primaryKey": false,
          "notNull": true,
          "default": false
        },
        "quality_tier": {
          "name": "quality_tier",
          "type": "text",
          "primaryKey": false,
          "notNull": false
        },
        "availability_rank": {
          "name": "availability_rank",
          "type": "integer",
          "primaryKey": false,
          "notNull": true,
          "default": 0
        },
        "quality_rank": {
          "name": "quality_rank",
          "type": "integer",
          "primaryKey": false,
          "notNull": true,
          "default": 0
        },
        "search_text": {
          "name": "search_text",
          "type": "text",
          "primaryKey": false,
          "notNull": true,
          "default": "''"
        },
        "search_vector": {
          "name": "search_vector",
          "type": "tsvector",
          "primaryKey": false,
          "notNull": false
        },
        "facet_payload": {
          "name": "facet_payload",
          "type": "jsonb",
          "primaryKey": false,
          "notNull": true,
          "default": "'{}'::jsonb"
        },
        "ranking_features": {
          "name": "ranking_features",
          "type": "jsonb",
          "primaryKey": false,
          "notNull": true,
          "default": "'{}'::jsonb"
        },
        "visible_attributes_payload": {
          "name": "visible_attributes_payload",
          "type": "jsonb",
          "primaryKey": false,
          "notNull": true,
          "default": "'{}'::jsonb"
        },
        "explain_payload": {
          "name": "explain_payload",
          "type": "jsonb",
          "primaryKey": false,
          "notNull": true,
          "default": "'{}'::jsonb"
        },
        "source_updated_at": {
          "name": "source_updated_at",
          "type": "timestamp with time zone",
          "primaryKey": false,
          "notNull": false
        },
        "indexed_at": {
          "name": "indexed_at",
          "type": "timestamp with time zone",
          "primaryKey": false,
          "notNull": false
        },
        "created_at": {
          "name": "created_at",
          "type": "timestamp with time zone",
          "primaryKey": false,
          "notNull": true,
          "default": "now()"
        },
        "updated_at": {
          "name": "updated_at",
          "type": "timestamp with time zone",
          "primaryKey": false,
          "notNull": true,
          "default": "now()"
        }
      },
      "indexes": {
        "catalog_search_documents_catalog_entry_unique": {
          "name": "catalog_search_documents_catalog_entry_unique",
          "columns": [
            {
              "expression": "catalog_entry_id",
              "isExpression": false,
              "asc": true,
              "nulls": "last"
            }
          ],
          "isUnique": true,
          "concurrently": false,
          "method": "btree",
          "with": {}
        },
        "catalog_search_documents_catalog_status_idx": {
          "name": "catalog_search_documents_catalog_status_idx",
          "columns": [
            {
              "expression": "catalog_id",
              "isExpression": false,
              "asc": true,
              "nulls": "last"
            },
            {
              "expression": "document_status",
              "isExpression": false,
              "asc": true,
              "nulls": "last"
            }
          ],
          "isUnique": false,
          "concurrently": false,
          "method": "btree",
          "with": {}
        },
        "catalog_search_documents_catalog_provider_status_idx": {
          "name": "catalog_search_documents_catalog_provider_status_idx",
          "columns": [
            {
              "expression": "catalog_id",
              "isExpression": false,
              "asc": true,
              "nulls": "last"
            },
            {
              "expression": "provider_id",
              "isExpression": false,
              "asc": true,
              "nulls": "last"
            },
            {
              "expression": "document_status",
              "isExpression": false,
              "asc": true,
              "nulls": "last"
            }
          ],
          "isUnique": false,
          "concurrently": false,
          "method": "btree",
          "with": {}
        },
        "catalog_search_documents_catalog_category_status_idx": {
          "name": "catalog_search_documents_catalog_category_status_idx",
          "columns": [
            {
              "expression": "catalog_id",
              "isExpression": false,
              "asc": true,
              "nulls": "last"
            },
            {
              "expression": "category",
              "isExpression": false,
              "asc": true,
              "nulls": "last"
            },
            {
              "expression": "document_status",
              "isExpression": false,
              "asc": true,
              "nulls": "last"
            }
          ],
          "isUnique": false,
          "concurrently": false,
          "method": "btree",
          "with": {}
        },
        "catalog_search_documents_catalog_brand_status_idx": {
          "name": "catalog_search_documents_catalog_brand_status_idx",
          "columns": [
            {
              "expression": "catalog_id",
              "isExpression": false,
              "asc": true,
              "nulls": "last"
            },
            {
              "expression": "brand",
              "isExpression": false,
              "asc": true,
              "nulls": "last"
            },
            {
              "expression": "document_status",
              "isExpression": false,
              "asc": true,
              "nulls": "last"
            }
          ],
          "isUnique": false,
          "concurrently": false,
          "method": "btree",
          "with": {}
        },
        "catalog_search_documents_catalog_availability_status_idx": {
          "name": "catalog_search_documents_catalog_availability_status_idx",
          "columns": [
            {
              "expression": "catalog_id",
              "isExpression": false,
              "asc": true,
              "nulls": "last"
            },
            {
              "expression": "availability_status",
              "isExpression": false,
              "asc": true,
              "nulls": "last"
            },
            {
              "expression": "document_status",
              "isExpression": false,
              "asc": true,
              "nulls": "last"
            }
          ],
          "isUnique": false,
          "concurrently": false,
          "method": "btree",
          "with": {}
        },
        "catalog_search_documents_catalog_sku_status_idx": {
          "name": "catalog_search_documents_catalog_sku_status_idx",
          "columns": [
            {
              "expression": "catalog_id",
              "isExpression": false,
              "asc": true,
              "nulls": "last"
            },
            {
              "expression": "sku",
              "isExpression": false,
              "asc": true,
              "nulls": "last"
            },
            {
              "expression": "document_status",
              "isExpression": false,
              "asc": true,
              "nulls": "last"
            }
          ],
          "isUnique": false,
          "concurrently": false,
          "method": "btree",
          "with": {}
        },
        "catalog_search_documents_catalog_currency_status_idx": {
          "name": "catalog_search_documents_catalog_currency_status_idx",
          "columns": [
            {
              "expression": "catalog_id",
              "isExpression": false,
              "asc": true,
              "nulls": "last"
            },
            {
              "expression": "currency",
              "isExpression": false,
              "asc": true,
              "nulls": "last"
            },
            {
              "expression": "document_status",
              "isExpression": false,
              "asc": true,
              "nulls": "last"
            }
          ],
          "isUnique": false,
          "concurrently": false,
          "method": "btree",
          "with": {}
        },
        "catalog_search_documents_catalog_amount_status_idx": {
          "name": "catalog_search_documents_catalog_amount_status_idx",
          "columns": [
            {
              "expression": "catalog_id",
              "isExpression": false,
              "asc": true,
              "nulls": "last"
            },
            {
              "expression": "amount",
              "isExpression": false,
              "asc": true,
              "nulls": "last"
            },
            {
              "expression": "document_status",
              "isExpression": false,
              "asc": true,
              "nulls": "last"
            }
          ],
          "isUnique": false,
          "concurrently": false,
          "method": "btree",
          "with": {}
        },
        "catalog_search_documents_catalog_quality_status_idx": {
          "name": "catalog_search_documents_catalog_quality_status_idx",
          "columns": [
            {
              "expression": "catalog_id",
              "isExpression": false,
              "asc": true,
              "nulls": "last"
            },
            {
              "expression": "quality_tier",
              "isExpression": false,
              "asc": true,
              "nulls": "last"
            },
            {
              "expression": "document_status",
              "isExpression": false,
              "asc": true,
              "nulls": "last"
            }
          ],
          "isUnique": false,
          "concurrently": false,
          "method": "btree",
          "with": {}
        },
        "catalog_search_documents_catalog_updated_idx": {
          "name": "catalog_search_documents_catalog_updated_idx",
          "columns": [
            {
              "expression": "catalog_id",
              "isExpression": false,
              "asc": true,
              "nulls": "last"
            },
            {
              "expression": "document_status",
              "isExpression": false,
              "asc": true,
              "nulls": "last"
            },
            {
              "expression": "updated_at",
              "isExpression": false,
              "asc": true,
              "nulls": "last"
            }
          ],
          "isUnique": false,
          "concurrently": false,
          "method": "btree",
          "with": {}
        }
      },
      "foreignKeys": {
        "catalog_search_documents_catalog_entry_id_catalog_entries_id_fk": {
          "name": "catalog_search_documents_catalog_entry_id_catalog_entries_id_fk",
          "tableFrom": "catalog_search_documents",
          "tableTo": "catalog_entries",
          "columnsFrom": [
            "catalog_entry_id"
          ],
          "columnsTo": [
            "id"
          ],
          "onDelete": "cascade",
          "onUpdate": "no action"
        },
        "catalog_search_documents_commercial_object_id_commercial_objects_id_fk": {
          "name": "catalog_search_documents_commercial_object_id_commercial_objects_id_fk",
          "tableFrom": "catalog_search_documents",
          "tableTo": "commercial_objects",
          "columnsFrom": [
            "commercial_object_id"
          ],
          "columnsTo": [
            "id"
          ],
          "onDelete": "cascade",
          "onUpdate": "no action"
        }
      },
      "compositePrimaryKeys": {},
      "uniqueConstraints": {},
      "policies": {},
      "checkConstraints": {},
      "isRLSEnabled": false
    },
    "public.catalog_search_embeddings": {
      "name": "catalog_search_embeddings",
      "schema": "",
      "columns": {
        "id": {
          "name": "id",
          "type": "text",
          "primaryKey": true,
          "notNull": true
        },
        "catalog_id": {
          "name": "catalog_id",
          "type": "text",
          "primaryKey": false,
          "notNull": true
        },
        "catalog_search_document_id": {
          "name": "catalog_search_document_id",
          "type": "text",
          "primaryKey": false,
          "notNull": true
        },
        "embedding_provider": {
          "name": "embedding_provider",
          "type": "text",
          "primaryKey": false,
          "notNull": true
        },
        "embedding_model": {
          "name": "embedding_model",
          "type": "text",
          "primaryKey": false,
          "notNull": true
        },
        "embedding_dimension": {
          "name": "embedding_dimension",
          "type": "integer",
          "primaryKey": false,
          "notNull": true
        },
        "embedding_text": {
          "name": "embedding_text",
          "type": "text",
          "primaryKey": false,
          "notNull": true
        },
        "embedding_text_hash": {
          "name": "embedding_text_hash",
          "type": "text",
          "primaryKey": false,
          "notNull": true
        },
        "embedding_vector": {
          "name": "embedding_vector",
          "type": "jsonb",
          "primaryKey": false,
          "notNull": true,
          "default": "'[]'::jsonb"
        },
        "embedding_vector_pg": {
          "name": "embedding_vector_pg",
          "type": "vector",
          "primaryKey": false,
          "notNull": false
        },
        "status": {
          "name": "status",
          "type": "text",
          "primaryKey": false,
          "notNull": true,
          "default": "'ready'"
        },
        "error": {
          "name": "error",
          "type": "text",
          "primaryKey": false,
          "notNull": false
        },
        "created_at": {
          "name": "created_at",
          "type": "timestamp with time zone",
          "primaryKey": false,
          "notNull": true,
          "default": "now()"
        },
        "updated_at": {
          "name": "updated_at",
          "type": "timestamp with time zone",
          "primaryKey": false,
          "notNull": true,
          "default": "now()"
        }
      },
      "indexes": {
        "catalog_search_embeddings_document_model_unique": {
          "name": "catalog_search_embeddings_document_model_unique",
          "columns": [
            {
              "expression": "catalog_search_document_id",
              "isExpression": false,
              "asc": true,
              "nulls": "last"
            },
            {
              "expression": "embedding_model",
              "isExpression": false,
              "asc": true,
              "nulls": "last"
            }
          ],
          "isUnique": true,
          "concurrently": false,
          "method": "btree",
          "with": {}
        },
        "catalog_search_embeddings_catalog_model_status_idx": {
          "name": "catalog_search_embeddings_catalog_model_status_idx",
          "columns": [
            {
              "expression": "catalog_id",
              "isExpression": false,
              "asc": true,
              "nulls": "last"
            },
            {
              "expression": "embedding_model",
              "isExpression": false,
              "asc": true,
              "nulls": "last"
            },
            {
              "expression": "status",
              "isExpression": false,
              "asc": true,
              "nulls": "last"
            }
          ],
          "isUnique": false,
          "concurrently": false,
          "method": "btree",
          "with": {}
        }
      },
      "foreignKeys": {
        "catalog_search_embeddings_catalog_search_document_id_catalog_search_documents_id_fk": {
          "name": "catalog_search_embeddings_catalog_search_document_id_catalog_search_documents_id_fk",
          "tableFrom": "catalog_search_embeddings",
          "tableTo": "catalog_search_documents",
          "columnsFrom": [
            "catalog_search_document_id"
          ],
          "columnsTo": [
            "id"
          ],
          "onDelete": "cascade",
          "onUpdate": "no action"
        }
      },
      "compositePrimaryKeys": {},
      "uniqueConstraints": {},
      "policies": {},
      "checkConstraints": {},
      "isRLSEnabled": false
    },
    "public.catalog_search_index_jobs": {
      "name": "catalog_search_index_jobs",
      "schema": "",
      "columns": {
        "id": {
          "name": "id",
          "type": "text",
          "primaryKey": true,
          "notNull": true
        },
        "catalog_id": {
          "name": "catalog_id",
          "type": "text",
          "primaryKey": false,
          "notNull": true
        },
        "provider_id": {
          "name": "provider_id",
          "type": "text",
          "primaryKey": false,
          "notNull": false
        },
        "catalog_entry_id": {
          "name": "catalog_entry_id",
          "type": "text",
          "primaryKey": false,
          "notNull": false
        },
        "commercial_object_id": {
          "name": "commercial_object_id",
          "type": "text",
          "primaryKey": false,
          "notNull": false
        },
        "job_type": {
          "name": "job_type",
          "type": "catalog_search_index_job_type",
          "typeSchema": "public",
          "primaryKey": false,
          "notNull": true
        },
        "status": {
          "name": "status",
          "type": "catalog_search_index_job_status",
          "typeSchema": "public",
          "primaryKey": false,
          "notNull": true,
          "default": "'pending'"
        },
        "attempt_count": {
          "name": "attempt_count",
          "type": "integer",
          "primaryKey": false,
          "notNull": true,
          "default": 0
        },
        "max_attempts": {
          "name": "max_attempts",
          "type": "integer",
          "primaryKey": false,
          "notNull": true,
          "default": 5
        },
        "scheduled_at": {
          "name": "scheduled_at",
          "type": "timestamp with time zone",
          "primaryKey": false,
          "notNull": true,
          "default": "now()"
        },
        "started_at": {
          "name": "started_at",
          "type": "timestamp with time zone",
          "primaryKey": false,
          "notNull": false
        },
        "finished_at": {
          "name": "finished_at",
          "type": "timestamp with time zone",
          "primaryKey": false,
          "notNull": false
        },
        "error": {
          "name": "error",
          "type": "text",
          "primaryKey": false,
          "notNull": false
        },
        "payload": {
          "name": "payload",
          "type": "jsonb",
          "primaryKey": false,
          "notNull": true,
          "default": "'{}'::jsonb"
        },
        "created_at": {
          "name": "created_at",
          "type": "timestamp with time zone",
          "primaryKey": false,
          "notNull": true,
          "default": "now()"
        },
        "updated_at": {
          "name": "updated_at",
          "type": "timestamp with time zone",
          "primaryKey": false,
          "notNull": true,
          "default": "now()"
        }
      },
      "indexes": {
        "catalog_search_index_jobs_catalog_status_scheduled_idx": {
          "name": "catalog_search_index_jobs_catalog_status_scheduled_idx",
          "columns": [
            {
              "expression": "catalog_id",
              "isExpression": false,
              "asc": true,
              "nulls": "last"
            },
            {
              "expression": "status",
              "isExpression": false,
              "asc": true,
              "nulls": "last"
            },
            {
              "expression": "scheduled_at",
              "isExpression": false,
              "asc": true,
              "nulls": "last"
            }
          ],
          "isUnique": false,
          "concurrently": false,
          "method": "btree",
          "with": {}
        },
        "catalog_search_index_jobs_catalog_type_status_idx": {
          "name": "catalog_search_index_jobs_catalog_type_status_idx",
          "columns": [
            {
              "expression": "catalog_id",
              "isExpression": false,
              "asc": true,
              "nulls": "last"
            },
            {
              "expression": "job_type",
              "isExpression": false,
              "asc": true,
              "nulls": "last"
            },
            {
              "expression": "status",
              "isExpression": false,
              "asc": true,
              "nulls": "last"
            }
          ],
          "isUnique": false,
          "concurrently": false,
          "method": "btree",
          "with": {}
        },
        "catalog_search_index_jobs_catalog_provider_created_idx": {
          "name": "catalog_search_index_jobs_catalog_provider_created_idx",
          "columns": [
            {
              "expression": "catalog_id",
              "isExpression": false,
              "asc": true,
              "nulls": "last"
            },
            {
              "expression": "provider_id",
              "isExpression": false,
              "asc": true,
              "nulls": "last"
            },
            {
              "expression": "created_at",
              "isExpression": false,
              "asc": true,
              "nulls": "last"
            }
          ],
          "isUnique": false,
          "concurrently": false,
          "method": "btree",
          "with": {}
        }
      },
      "foreignKeys": {
        "catalog_search_index_jobs_catalog_entry_id_catalog_entries_id_fk": {
          "name": "catalog_search_index_jobs_catalog_entry_id_catalog_entries_id_fk",
          "tableFrom": "catalog_search_index_jobs",
          "tableTo": "catalog_entries",
          "columnsFrom": [
            "catalog_entry_id"
          ],
          "columnsTo": [
            "id"
          ],
          "onDelete": "set null",
          "onUpdate": "no action"
        },
        "catalog_search_index_jobs_commercial_object_id_commercial_objects_id_fk": {
          "name": "catalog_search_index_jobs_commercial_object_id_commercial_objects_id_fk",
          "tableFrom": "catalog_search_index_jobs",
          "tableTo": "commercial_objects",
          "columnsFrom": [
            "commercial_object_id"
          ],
          "columnsTo": [
            "id"
          ],
          "onDelete": "set null",
          "onUpdate": "no action"
        }
      },
      "compositePrimaryKeys": {},
      "uniqueConstraints": {},
      "policies": {},
      "checkConstraints": {},
      "isRLSEnabled": false
    },
    "public.commercial_objects": {
      "name": "commercial_objects",
      "schema": "",
      "columns": {
        "id": {
          "name": "id",
          "type": "text",
          "primaryKey": true,
          "notNull": true
        },
        "catalog_id": {
          "name": "catalog_id",
          "type": "text",
          "primaryKey": false,
          "notNull": true
        },
        "provider_id": {
          "name": "provider_id",
          "type": "text",
          "primaryKey": false,
          "notNull": true
        },
        "object_id": {
          "name": "object_id",
          "type": "text",
          "primaryKey": false,
          "notNull": true
        },
        "object_type": {
          "name": "object_type",
          "type": "text",
          "primaryKey": false,
          "notNull": true
        },
        "title": {
          "name": "title",
          "type": "text",
          "primaryKey": false,
          "notNull": true
        },
        "summary": {
          "name": "summary",
          "type": "text",
          "primaryKey": false,
          "notNull": false
        },
        "status": {
          "name": "status",
          "type": "text",
          "primaryKey": false,
          "notNull": true,
          "default": "'active'"
        },
        "source_url": {
          "name": "source_url",
          "type": "text",
          "primaryKey": false,
          "notNull": false
        },
        "raw_object": {
          "name": "raw_object",
          "type": "jsonb",
          "primaryKey": false,
          "notNull": true
        },
        "created_at": {
          "name": "created_at",
          "type": "timestamp with time zone",
          "primaryKey": false,
          "notNull": true,
          "default": "now()"
        },
        "updated_at": {
          "name": "updated_at",
          "type": "timestamp with time zone",
          "primaryKey": false,
          "notNull": true,
          "default": "now()"
        }
      },
      "indexes": {
        "commercial_objects_provider_object_unique": {
          "name": "commercial_objects_provider_object_unique",
          "columns": [
            {
              "expression": "catalog_id",
              "isExpression": false,
              "asc": true,
              "nulls": "last"
            },
            {
              "expression": "provider_id",
              "isExpression": false,
              "asc": true,
              "nulls": "last"
            },
            {
              "expression": "object_id",
              "isExpression": false,
              "asc": true,
              "nulls": "last"
            }
          ],
          "isUnique": true,
          "concurrently": false,
          "method": "btree",
          "with": {}
        },
        "commercial_objects_catalog_type_idx": {
          "name": "commercial_objects_catalog_type_idx",
          "columns": [
            {
              "expression": "catalog_id",
              "isExpression": false,
              "asc": true,
              "nulls": "last"
            },
            {
              "expression": "object_type",
              "isExpression": false,
              "asc": true,
              "nulls": "last"
            }
          ],
          "isUnique": false,
          "concurrently": false,
          "method": "btree",
          "with": {}
        }
      },
      "foreignKeys": {},
      "compositePrimaryKeys": {},
      "uniqueConstraints": {},
      "policies": {},
      "checkConstraints": {},
      "isRLSEnabled": false
    },
    "public.descriptor_instances": {
      "name": "descriptor_instances",
      "schema": "",
      "columns": {
        "id": {
          "name": "id",
          "type": "text",
          "primaryKey": true,
          "notNull": true
        },
        "commercial_object_id": {
          "name": "commercial_object_id",
          "type": "text",
          "primaryKey": false,
          "notNull": true
        },
        "pack_id": {
          "name": "pack_id",
          "type": "text",
          "primaryKey": false,
          "notNull": true
        },
        "schema_uri": {
          "name": "schema_uri",
          "type": "text",
          "primaryKey": false,
          "notNull": false
        },
        "payload": {
          "name": "payload",
          "type": "jsonb",
          "primaryKey": false,
          "notNull": true
        },
        "created_at": {
          "name": "created_at",
          "type": "timestamp with time zone",
          "primaryKey": false,
          "notNull": true,
          "default": "now()"
        },
        "updated_at": {
          "name": "updated_at",
          "type": "timestamp with time zone",
          "primaryKey": false,
          "notNull": true,
          "default": "now()"
        }
      },
      "indexes": {
        "descriptor_instances_object_pack_idx": {
          "name": "descriptor_instances_object_pack_idx",
          "columns": [
            {
              "expression": "commercial_object_id",
              "isExpression": false,
              "asc": true,
              "nulls": "last"
            },
            {
              "expression": "pack_id",
              "isExpression": false,
              "asc": true,
              "nulls": "last"
            }
          ],
          "isUnique": false,
          "concurrently": false,
          "method": "btree",
          "with": {}
        }
      },
      "foreignKeys": {
        "descriptor_instances_commercial_object_id_commercial_objects_id_fk": {
          "name": "descriptor_instances_commercial_object_id_commercial_objects_id_fk",
          "tableFrom": "descriptor_instances",
          "tableTo": "commercial_objects",
          "columnsFrom": [
            "commercial_object_id"
          ],
          "columnsTo": [
            "id"
          ],
          "onDelete": "cascade",
          "onUpdate": "no action"
        }
      },
      "compositePrimaryKeys": {},
      "uniqueConstraints": {},
      "policies": {},
      "checkConstraints": {},
      "isRLSEnabled": false
    },
    "public.object_contracts": {
      "name": "object_contracts",
      "schema": "",
      "columns": {
        "id": {
          "name": "id",
          "type": "text",
          "primaryKey": true,
          "notNull": true
        },
        "catalog_id": {
          "name": "catalog_id",
          "type": "text",
          "primaryKey": false,
          "notNull": true
        },
        "contract_id": {
          "name": "contract_id",
          "type": "text",
          "primaryKey": false,
          "notNull": true
        },
        "object_type": {
          "name": "object_type",
          "type": "text",
          "primaryKey": false,
          "notNull": true
        },
        "contract": {
          "name": "contract",
          "type": "jsonb",
          "primaryKey": false,
          "notNull": true
        },
        "version": {
          "name": "version",
          "type": "integer",
          "primaryKey": false,
          "notNull": true,
          "default": 1
        },
        "created_at": {
          "name": "created_at",
          "type": "timestamp with time zone",
          "primaryKey": false,
          "notNull": true,
          "default": "now()"
        },
        "updated_at": {
          "name": "updated_at",
          "type": "timestamp with time zone",
          "primaryKey": false,
          "notNull": true,
          "default": "now()"
        }
      },
      "indexes": {
        "object_contracts_catalog_contract_unique": {
          "name": "object_contracts_catalog_contract_unique",
          "columns": [
            {
              "expression": "catalog_id",
              "isExpression": false,
              "asc": true,
              "nulls": "last"
            },
            {
              "expression": "contract_id",
              "isExpression": false,
              "asc": true,
              "nulls": "last"
            }
          ],
          "isUnique": true,
          "concurrently": false,
          "method": "btree",
          "with": {}
        },
        "object_contracts_catalog_object_type_idx": {
          "name": "object_contracts_catalog_object_type_idx",
          "columns": [
            {
              "expression": "catalog_id",
              "isExpression": false,
              "asc": true,
              "nulls": "last"
            },
            {
              "expression": "object_type",
              "isExpression": false,
              "asc": true,
              "nulls": "last"
            }
          ],
          "isUnique": false,
          "concurrently": false,
          "method": "btree",
          "with": {}
        }
      },
      "foreignKeys": {},
      "compositePrimaryKeys": {},
      "uniqueConstraints": {},
      "policies": {},
      "checkConstraints": {},
      "isRLSEnabled": false
    },
    "public.object_sync_batches": {
      "name": "object_sync_batches",
      "schema": "",
      "columns": {
        "id": {
          "name": "id",
          "type": "text",
          "primaryKey": true,
          "notNull": true
        },
        "catalog_id": {
          "name": "catalog_id",
          "type": "text",
          "primaryKey": false,
          "notNull": true
        },
        "provider_id": {
          "name": "provider_id",
          "type": "text",
          "primaryKey": false,
          "notNull": true
        },
        "registration_version": {
          "name": "registration_version",
          "type": "integer",
          "primaryKey": false,
          "notNull": true
        },
        "batch_id": {
          "name": "batch_id",
          "type": "text",
          "primaryKey": false,
          "notNull": true
        },
        "status": {
          "name": "status",
          "type": "object_sync_batch_status",
          "typeSchema": "public",
          "primaryKey": false,
          "notNull": true,
          "default": "'rejected'"
        },
        "accepted_count": {
          "name": "accepted_count",
          "type": "integer",
          "primaryKey": false,
          "notNull": true,
          "default": 0
        },
        "rejected_count": {
          "name": "rejected_count",
          "type": "integer",
          "primaryKey": false,
          "notNull": true,
          "default": 0
        },
        "error_count": {
          "name": "error_count",
          "type": "integer",
          "primaryKey": false,
          "notNull": true,
          "default": 0
        },
        "request_payload": {
          "name": "request_payload",
          "type": "jsonb",
          "primaryKey": false,
          "notNull": true
        },
        "result_payload": {
          "name": "result_payload",
          "type": "jsonb",
          "primaryKey": false,
          "notNull": false
        },
        "created_at": {
          "name": "created_at",
          "type": "timestamp with time zone",
          "primaryKey": false,
          "notNull": true,
          "default": "now()"
        },
        "finished_at": {
          "name": "finished_at",
          "type": "timestamp with time zone",
          "primaryKey": false,
          "notNull": false
        }
      },
      "indexes": {
        "object_sync_batches_provider_batch_unique": {
          "name": "object_sync_batches_provider_batch_unique",
          "columns": [
            {
              "expression": "catalog_id",
              "isExpression": false,
              "asc": true,
              "nulls": "last"
            },
            {
              "expression": "provider_id",
              "isExpression": false,
              "asc": true,
              "nulls": "last"
            },
            {
              "expression": "batch_id",
              "isExpression": false,
              "asc": true,
              "nulls": "last"
            }
          ],
          "isUnique": true,
          "concurrently": false,
          "method": "btree",
          "with": {}
        },
        "object_sync_batches_provider_created_idx": {
          "name": "object_sync_batches_provider_created_idx",
          "columns": [
            {
              "expression": "catalog_id",
              "isExpression": false,
              "asc": true,
              "nulls": "last"
            },
            {
              "expression": "provider_id",
              "isExpression": false,
              "asc": true,
              "nulls": "last"
            },
            {
              "expression": "created_at",
              "isExpression": false,
              "asc": true,
              "nulls": "last"
            }
          ],
          "isUnique": false,
          "concurrently": false,
          "method": "btree",
          "with": {}
        }
      },
      "foreignKeys": {},
      "compositePrimaryKeys": {},
      "uniqueConstraints": {},
      "policies": {},
      "checkConstraints": {},
      "isRLSEnabled": false
    },
    "public.object_sync_item_results": {
      "name": "object_sync_item_results",
      "schema": "",
      "columns": {
        "id": {
          "name": "id",
          "type": "text",
          "primaryKey": true,
          "notNull": true
        },
        "sync_batch_id": {
          "name": "sync_batch_id",
          "type": "text",
          "primaryKey": false,
          "notNull": true
        },
        "object_id": {
          "name": "object_id",
          "type": "text",
          "primaryKey": false,
          "notNull": false
        },
        "status": {
          "name": "status",
          "type": "object_sync_item_status",
          "typeSchema": "public",
          "primaryKey": false,
          "notNull": true
        },
        "commercial_object_id": {
          "name": "commercial_object_id",
          "type": "text",
          "primaryKey": false,
          "notNull": false
        },
        "catalog_entry_id": {
          "name": "catalog_entry_id",
          "type": "text",
          "primaryKey": false,
          "notNull": false
        },
        "errors": {
          "name": "errors",
          "type": "jsonb",
          "primaryKey": false,
          "notNull": true,
          "default": "'[]'::jsonb"
        },
        "warnings": {
          "name": "warnings",
          "type": "jsonb",
          "primaryKey": false,
          "notNull": true,
          "default": "'[]'::jsonb"
        },
        "created_at": {
          "name": "created_at",
          "type": "timestamp with time zone",
          "primaryKey": false,
          "notNull": true,
          "default": "now()"
        }
      },
      "indexes": {
        "object_sync_item_results_batch_idx": {
          "name": "object_sync_item_results_batch_idx",
          "columns": [
            {
              "expression": "sync_batch_id",
              "isExpression": false,
              "asc": true,
              "nulls": "last"
            }
          ],
          "isUnique": false,
          "concurrently": false,
          "method": "btree",
          "with": {}
        }
      },
      "foreignKeys": {
        "object_sync_item_results_sync_batch_id_object_sync_batches_id_fk": {
          "name": "object_sync_item_results_sync_batch_id_object_sync_batches_id_fk",
          "tableFrom": "object_sync_item_results",
          "tableTo": "object_sync_batches",
          "columnsFrom": [
            "sync_batch_id"
          ],
          "columnsTo": [
            "id"
          ],
          "onDelete": "cascade",
          "onUpdate": "no action"
        },
        "object_sync_item_results_commercial_object_id_commercial_objects_id_fk": {
          "name": "object_sync_item_results_commercial_object_id_commercial_objects_id_fk",
          "tableFrom": "object_sync_item_results",
          "tableTo": "commercial_objects",
          "columnsFrom": [
            "commercial_object_id"
          ],
          "columnsTo": [
            "id"
          ],
          "onDelete": "set null",
          "onUpdate": "no action"
        },
        "object_sync_item_results_catalog_entry_id_catalog_entries_id_fk": {
          "name": "object_sync_item_results_catalog_entry_id_catalog_entries_id_fk",
          "tableFrom": "object_sync_item_results",
          "tableTo": "catalog_entries",
          "columnsFrom": [
            "catalog_entry_id"
          ],
          "columnsTo": [
            "id"
          ],
          "onDelete": "set null",
          "onUpdate": "no action"
        }
      },
      "compositePrimaryKeys": {},
      "uniqueConstraints": {},
      "policies": {},
      "checkConstraints": {},
      "isRLSEnabled": false
    },
    "public.provider_contract_states": {
      "name": "provider_contract_states",
      "schema": "",
      "columns": {
        "id": {
          "name": "id",
          "type": "text",
          "primaryKey": true,
          "notNull": true
        },
        "catalog_id": {
          "name": "catalog_id",
          "type": "text",
          "primaryKey": false,
          "notNull": true
        },
        "provider_id": {
          "name": "provider_id",
          "type": "text",
          "primaryKey": false,
          "notNull": true
        },
        "active_registration_id": {
          "name": "active_registration_id",
          "type": "text",
          "primaryKey": false,
          "notNull": true
        },
        "active_registration_version": {
          "name": "active_registration_version",
          "type": "integer",
          "primaryKey": false,
          "notNull": true
        },
        "status": {
          "name": "status",
          "type": "provider_contract_state_status",
          "typeSchema": "public",
          "primaryKey": false,
          "notNull": true,
          "default": "'active'"
        },
        "declared_object_types": {
          "name": "declared_object_types",
          "type": "jsonb",
          "primaryKey": false,
          "notNull": true,
          "default": "'[]'::jsonb"
        },
        "declared_packs": {
          "name": "declared_packs",
          "type": "jsonb",
          "primaryKey": false,
          "notNull": true,
          "default": "'[]'::jsonb"
        },
        "guaranteed_fields": {
          "name": "guaranteed_fields",
          "type": "jsonb",
          "primaryKey": false,
          "notNull": true,
          "default": "'[]'::jsonb"
        },
        "created_at": {
          "name": "created_at",
          "type": "timestamp with time zone",
          "primaryKey": false,
          "notNull": true,
          "default": "now()"
        },
        "updated_at": {
          "name": "updated_at",
          "type": "timestamp with time zone",
          "primaryKey": false,
          "notNull": true,
          "default": "now()"
        }
      },
      "indexes": {
        "provider_contract_states_provider_unique": {
          "name": "provider_contract_states_provider_unique",
          "columns": [
            {
              "expression": "catalog_id",
              "isExpression": false,
              "asc": true,
              "nulls": "last"
            },
            {
              "expression": "provider_id",
              "isExpression": false,
              "asc": true,
              "nulls": "last"
            }
          ],
          "isUnique": true,
          "concurrently": false,
          "method": "btree",
          "with": {}
        },
        "provider_contract_states_active_registration_idx": {
          "name": "provider_contract_states_active_registration_idx",
          "columns": [
            {
              "expression": "active_registration_id",
              "isExpression": false,
              "asc": true,
              "nulls": "last"
            }
          ],
          "isUnique": false,
          "concurrently": false,
          "method": "btree",
          "with": {}
        }
      },
      "foreignKeys": {
        "provider_contract_states_active_registration_id_provider_registrations_id_fk": {
          "name": "provider_contract_states_active_registration_id_provider_registrations_id_fk",
          "tableFrom": "provider_contract_states",
          "tableTo": "provider_registrations",
          "columnsFrom": [
            "active_registration_id"
          ],
          "columnsTo": [
            "id"
          ],
          "onDelete": "restrict",
          "onUpdate": "no action"
        }
      },
      "compositePrimaryKeys": {},
      "uniqueConstraints": {},
      "policies": {},
      "checkConstraints": {},
      "isRLSEnabled": false
    },
    "public.provider_registrations": {
      "name": "provider_registrations",
      "schema": "",
      "columns": {
        "id": {
          "name": "id",
          "type": "text",
          "primaryKey": true,
          "notNull": true
        },
        "catalog_id": {
          "name": "catalog_id",
          "type": "text",
          "primaryKey": false,
          "notNull": true
        },
        "provider_id": {
          "name": "provider_id",
          "type": "text",
          "primaryKey": false,
          "notNull": true
        },
        "registration_version": {
          "name": "registration_version",
          "type": "integer",
          "primaryKey": false,
          "notNull": true
        },
        "status": {
          "name": "status",
          "type": "registration_status",
          "typeSchema": "public",
          "primaryKey": false,
          "notNull": true,
          "default": "'pending_verification'"
        },
        "registration": {
          "name": "registration",
          "type": "jsonb",
          "primaryKey": false,
          "notNull": true
        },
        "result": {
          "name": "result",
          "type": "jsonb",
          "primaryKey": false,
          "notNull": false
        },
        "source_ip": {
          "name": "source_ip",
          "type": "text",
          "primaryKey": false,
          "notNull": false
        },
        "user_agent": {
          "name": "user_agent",
          "type": "text",
          "primaryKey": false,
          "notNull": false
        },
        "created_at": {
          "name": "created_at",
          "type": "timestamp with time zone",
          "primaryKey": false,
          "notNull": true,
          "default": "now()"
        },
        "updated_at": {
          "name": "updated_at",
          "type": "timestamp with time zone",
          "primaryKey": false,
          "notNull": true,
          "default": "now()"
        }
      },
      "indexes": {
        "provider_registrations_provider_version_unique": {
          "name": "provider_registrations_provider_version_unique",
          "columns": [
            {
              "expression": "catalog_id",
              "isExpression": false,
              "asc": true,
              "nulls": "last"
            },
            {
              "expression": "provider_id",
              "isExpression": false,
              "asc": true,
              "nulls": "last"
            },
            {
              "expression": "registration_version",
              "isExpression": false,
              "asc": true,
              "nulls": "last"
            }
          ],
          "isUnique": true,
          "concurrently": false,
          "method": "btree",
          "with": {}
        },
        "provider_registrations_provider_idx": {
          "name": "provider_registrations_provider_idx",
          "columns": [
            {
              "expression": "catalog_id",
              "isExpression": false,
              "asc": true,
              "nulls": "last"
            },
            {
              "expression": "provider_id",
              "isExpression": false,
              "asc": true,
              "nulls": "last"
            }
          ],
          "isUnique": false,
          "concurrently": false,
          "method": "btree",
          "with": {}
        }
      },
      "foreignKeys": {},
      "compositePrimaryKeys": {},
      "uniqueConstraints": {},
      "policies": {},
      "checkConstraints": {},
      "isRLSEnabled": false
    },
    "public.query_audit_records": {
      "name": "query_audit_records",
      "schema": "",
      "columns": {
        "id": {
          "name": "id",
          "type": "text",
          "primaryKey": true,
          "notNull": true
        },
        "catalog_id": {
          "name": "catalog_id",
          "type": "text",
          "primaryKey": false,
          "notNull": true
        },
        "query_kind": {
          "name": "query_kind",
          "type": "text",
          "primaryKey": false,
          "notNull": true
        },
        "request_payload": {
          "name": "request_payload",
          "type": "jsonb",
          "primaryKey": false,
          "notNull": true
        },
        "result_count": {
          "name": "result_count",
          "type": "integer",
          "primaryKey": false,
          "notNull": true,
          "default": 0
        },
        "requester_key_hash": {
          "name": "requester_key_hash",
          "type": "text",
          "primaryKey": false,
          "notNull": false
        },
        "created_at": {
          "name": "created_at",
          "type": "timestamp with time zone",
          "primaryKey": false,
          "notNull": true,
          "default": "now()"
        }
      },
      "indexes": {
        "query_audit_records_catalog_created_idx": {
          "name": "query_audit_records_catalog_created_idx",
          "columns": [
            {
              "expression": "catalog_id",
              "isExpression": false,
              "asc": true,
              "nulls": "last"
            },
            {
              "expression": "created_at",
              "isExpression": false,
              "asc": true,
              "nulls": "last"
            }
          ],
          "isUnique": false,
          "concurrently": false,
          "method": "btree",
          "with": {}
        }
      },
      "foreignKeys": {},
      "compositePrimaryKeys": {},
      "uniqueConstraints": {},
      "policies": {},
      "checkConstraints": {},
      "isRLSEnabled": false
    },
    "public.resolvable_references": {
      "name": "resolvable_references",
      "schema": "",
      "columns": {
        "id": {
          "name": "id",
          "type": "text",
          "primaryKey": true,
          "notNull": true
        },
        "catalog_id": {
          "name": "catalog_id",
          "type": "text",
          "primaryKey": false,
          "notNull": true
        },
        "commercial_object_id": {
          "name": "commercial_object_id",
          "type": "text",
          "primaryKey": false,
          "notNull": true
        },
        "catalog_entry_id": {
          "name": "catalog_entry_id",
          "type": "text",
          "primaryKey": false,
          "notNull": false
        },
        "reference_type": {
          "name": "reference_type",
          "type": "text",
          "primaryKey": false,
          "notNull": true,
          "default": "'commercial_object'"
        },
        "resolved_title": {
          "name": "resolved_title",
          "type": "text",
          "primaryKey": false,
          "notNull": true
        },
        "payload": {
          "name": "payload",
          "type": "jsonb",
          "primaryKey": false,
          "notNull": true
        },
        "expires_at": {
          "name": "expires_at",
          "type": "timestamp with time zone",
          "primaryKey": false,
          "notNull": false
        },
        "created_at": {
          "name": "created_at",
          "type": "timestamp with time zone",
          "primaryKey": false,
          "notNull": true,
          "default": "now()"
        }
      },
      "indexes": {},
      "foreignKeys": {
        "resolvable_references_commercial_object_id_commercial_objects_id_fk": {
          "name": "resolvable_references_commercial_object_id_commercial_objects_id_fk",
          "tableFrom": "resolvable_references",
          "tableTo": "commercial_objects",
          "columnsFrom": [
            "commercial_object_id"
          ],
          "columnsTo": [
            "id"
          ],
          "onDelete": "cascade",
          "onUpdate": "no action"
        },
        "resolvable_references_catalog_entry_id_catalog_entries_id_fk": {
          "name": "resolvable_references_catalog_entry_id_catalog_entries_id_fk",
          "tableFrom": "resolvable_references",
          "tableTo": "catalog_entries",
          "columnsFrom": [
            "catalog_entry_id"
          ],
          "columnsTo": [
            "id"
          ],
          "onDelete": "set null",
          "onUpdate": "no action"
        }
      },
      "compositePrimaryKeys": {},
      "uniqueConstraints": {},
      "policies": {},
      "checkConstraints": {},
      "isRLSEnabled": false
    },
    "public.provider_products": {
      "name": "provider_products",
      "schema": "",
      "columns": {
        "id": {
          "name": "id",
          "type": "text",
          "primaryKey": true,
          "notNull": true
        },
        "provider_id": {
          "name": "provider_id",
          "type": "text",
          "primaryKey": false,
          "notNull": true
        },
        "sku": {
          "name": "sku",
          "type": "text",
          "primaryKey": false,
          "notNull": true
        },
        "title": {
          "name": "title",
          "type": "text",
          "primaryKey": false,
          "notNull": true
        },
        "summary": {
          "name": "summary",
          "type": "text",
          "primaryKey": false,
          "notNull": true
        },
        "brand": {
          "name": "brand",
          "type": "text",
          "primaryKey": false,
          "notNull": true
        },
        "category": {
          "name": "category",
          "type": "text",
          "primaryKey": false,
          "notNull": true
        },
        "product_url": {
          "name": "product_url",
          "type": "text",
          "primaryKey": false,
          "notNull": true
        },
        "image_urls": {
          "name": "image_urls",
          "type": "jsonb",
          "primaryKey": false,
          "notNull": true,
          "default": "'[]'::jsonb"
        },
        "currency": {
          "name": "currency",
          "type": "text",
          "primaryKey": false,
          "notNull": true
        },
        "amount_cents": {
          "name": "amount_cents",
          "type": "integer",
          "primaryKey": false,
          "notNull": true
        },
        "availability_status": {
          "name": "availability_status",
          "type": "text",
          "primaryKey": false,
          "notNull": true
        },
        "quantity": {
          "name": "quantity",
          "type": "integer",
          "primaryKey": false,
          "notNull": true,
          "default": 0
        },
        "status": {
          "name": "status",
          "type": "text",
          "primaryKey": false,
          "notNull": true,
          "default": "'active'"
        },
        "attributes": {
          "name": "attributes",
          "type": "jsonb",
          "primaryKey": false,
          "notNull": true,
          "default": "'{}'::jsonb"
        },
        "created_at": {
          "name": "created_at",
          "type": "timestamp with time zone",
          "primaryKey": false,
          "notNull": true,
          "default": "now()"
        },
        "updated_at": {
          "name": "updated_at",
          "type": "timestamp with time zone",
          "primaryKey": false,
          "notNull": true,
          "default": "now()"
        }
      },
      "indexes": {
        "provider_products_provider_sku_unique": {
          "name": "provider_products_provider_sku_unique",
          "columns": [
            {
              "expression": "provider_id",
              "isExpression": false,
              "asc": true,
              "nulls": "last"
            },
            {
              "expression": "sku",
              "isExpression": false,
              "asc": true,
              "nulls": "last"
            }
          ],
          "isUnique": true,
          "concurrently": false,
          "method": "btree",
          "with": {}
        },
        "provider_products_provider_status_idx": {
          "name": "provider_products_provider_status_idx",
          "columns": [
            {
              "expression": "provider_id",
              "isExpression": false,
              "asc": true,
              "nulls": "last"
            },
            {
              "expression": "status",
              "isExpression": false,
              "asc": true,
              "nulls": "last"
            }
          ],
          "isUnique": false,
          "concurrently": false,
          "method": "btree",
          "with": {}
        }
      },
      "foreignKeys": {},
      "compositePrimaryKeys": {},
      "uniqueConstraints": {},
      "policies": {},
      "checkConstraints": {},
      "isRLSEnabled": false
    },
    "public.provider_sync_runs": {
      "name": "provider_sync_runs",
      "schema": "",
      "columns": {
        "id": {
          "name": "id",
          "type": "text",
          "primaryKey": true,
          "notNull": true
        },
        "provider_id": {
          "name": "provider_id",
          "type": "text",
          "primaryKey": false,
          "notNull": true
        },
        "run_type": {
          "name": "run_type",
          "type": "text",
          "primaryKey": false,
          "notNull": true
        },
        "target_product_id": {
          "name": "target_product_id",
          "type": "text",
          "primaryKey": false,
          "notNull": false
        },
        "registration_version": {
          "name": "registration_version",
          "type": "integer",
          "primaryKey": false,
          "notNull": false
        },
        "status": {
          "name": "status",
          "type": "text",
          "primaryKey": false,
          "notNull": true
        },
        "request_payload": {
          "name": "request_payload",
          "type": "jsonb",
          "primaryKey": false,
          "notNull": false
        },
        "result_payload": {
          "name": "result_payload",
          "type": "jsonb",
          "primaryKey": false,
          "notNull": false
        },
        "error": {
          "name": "error",
          "type": "text",
          "primaryKey": false,
          "notNull": false
        },
        "created_at": {
          "name": "created_at",
          "type": "timestamp with time zone",
          "primaryKey": false,
          "notNull": true,
          "default": "now()"
        },
        "finished_at": {
          "name": "finished_at",
          "type": "timestamp with time zone",
          "primaryKey": false,
          "notNull": false
        }
      },
      "indexes": {
        "provider_sync_runs_provider_created_idx": {
          "name": "provider_sync_runs_provider_created_idx",
          "columns": [
            {
              "expression": "provider_id",
              "isExpression": false,
              "asc": true,
              "nulls": "last"
            },
            {
              "expression": "created_at",
              "isExpression": false,
              "asc": true,
              "nulls": "last"
            }
          ],
          "isUnique": false,
          "concurrently": false,
          "method": "btree",
          "with": {}
        }
      },
      "foreignKeys": {},
      "compositePrimaryKeys": {},
      "uniqueConstraints": {},
      "policies": {},
      "checkConstraints": {},
      "isRLSEnabled": false
    },
    "public.catalog_health_checks": {
      "name": "catalog_health_checks",
      "schema": "",
      "columns": {
        "id": {
          "name": "id",
          "type": "text",
          "primaryKey": true,
          "notNull": true
        },
        "center_id": {
          "name": "center_id",
          "type": "text",
          "primaryKey": false,
          "notNull": true
        },
        "catalog_id": {
          "name": "catalog_id",
          "type": "text",
          "primaryKey": false,
          "notNull": true
        },
        "checked_url": {
          "name": "checked_url",
          "type": "text",
          "primaryKey": false,
          "notNull": true
        },
        "status": {
          "name": "status",
          "type": "text",
          "primaryKey": false,
          "notNull": true
        },
        "latency_ms": {
          "name": "latency_ms",
          "type": "integer",
          "primaryKey": false,
          "notNull": false
        },
        "error": {
          "name": "error",
          "type": "text",
          "primaryKey": false,
          "notNull": false
        },
        "checked_at": {
          "name": "checked_at",
          "type": "timestamp with time zone",
          "primaryKey": false,
          "notNull": true,
          "default": "now()"
        }
      },
      "indexes": {
        "catalog_health_checks_catalog_idx": {
          "name": "catalog_health_checks_catalog_idx",
          "columns": [
            {
              "expression": "center_id",
              "isExpression": false,
              "asc": true,
              "nulls": "last"
            },
            {
              "expression": "catalog_id",
              "isExpression": false,
              "asc": true,
              "nulls": "last"
            },
            {
              "expression": "checked_at",
              "isExpression": false,
              "asc": true,
              "nulls": "last"
            }
          ],
          "isUnique": false,
          "concurrently": false,
          "method": "btree",
          "with": {}
        }
      },
      "foreignKeys": {},
      "compositePrimaryKeys": {},
      "uniqueConstraints": {},
      "policies": {},
      "checkConstraints": {},
      "isRLSEnabled": false
    },
    "public.catalog_index_entries": {
      "name": "catalog_index_entries",
      "schema": "",
      "columns": {
        "id": {
          "name": "id",
          "type": "text",
          "primaryKey": true,
          "notNull": true
        },
        "center_id": {
          "name": "center_id",
          "type": "text",
          "primaryKey": false,
          "notNull": true
        },
        "catalog_id": {
          "name": "catalog_id",
          "type": "text",
          "primaryKey": false,
          "notNull": true
        },
        "active_snapshot_id": {
          "name": "active_snapshot_id",
          "type": "text",
          "primaryKey": false,
          "notNull": true
        },
        "entry_status": {
          "name": "entry_status",
          "type": "text",
          "primaryKey": false,
          "notNull": true,
          "default": "'active'"
        },
        "catalog_name": {
          "name": "catalog_name",
          "type": "text",
          "primaryKey": false,
          "notNull": true
        },
        "description": {
          "name": "description",
          "type": "text",
          "primaryKey": false,
          "notNull": false
        },
        "homepage": {
          "name": "homepage",
          "type": "text",
          "primaryKey": false,
          "notNull": true
        },
        "manifest_url": {
          "name": "manifest_url",
          "type": "text",
          "primaryKey": false,
          "notNull": true
        },
        "well_known_url": {
          "name": "well_known_url",
          "type": "text",
          "primaryKey": false,
          "notNull": true
        },
        "tags": {
          "name": "tags",
          "type": "jsonb",
          "primaryKey": false,
          "notNull": true,
          "default": "'[]'::jsonb"
        },
        "domains": {
          "name": "domains",
          "type": "jsonb",
          "primaryKey": false,
          "notNull": true,
          "default": "'[]'::jsonb"
        },
        "supported_object_types": {
          "name": "supported_object_types",
          "type": "jsonb",
          "primaryKey": false,
          "notNull": true,
          "default": "'[]'::jsonb"
        },
        "supported_query_modes": {
          "name": "supported_query_modes",
          "type": "jsonb",
          "primaryKey": false,
          "notNull": true,
          "default": "'[]'::jsonb"
        },
        "supported_query_packs": {
          "name": "supported_query_packs",
          "type": "jsonb",
          "primaryKey": false,
          "notNull": true,
          "default": "'[]'::jsonb"
        },
        "supported_query_languages": {
          "name": "supported_query_languages",
          "type": "jsonb",
          "primaryKey": false,
          "notNull": true,
          "default": "'[]'::jsonb"
        },
        "content_languages": {
          "name": "content_languages",
          "type": "jsonb",
          "primaryKey": false,
          "notNull": true,
          "default": "'[]'::jsonb"
        },
        "supports_resolve": {
          "name": "supports_resolve",
          "type": "integer",
          "primaryKey": false,
          "notNull": true,
          "default": 0
        },
        "verification_status": {
          "name": "verification_status",
          "type": "text",
          "primaryKey": false,
          "notNull": true
        },
        "trust_tier": {
          "name": "trust_tier",
          "type": "text",
          "primaryKey": false,
          "notNull": true
        },
        "health_status": {
          "name": "health_status",
          "type": "text",
          "primaryKey": false,
          "notNull": true
        },
        "search_projection": {
          "name": "search_projection",
          "type": "jsonb",
          "primaryKey": false,
          "notNull": true,
          "default": "'{}'::jsonb"
        },
        "explain_projection": {
          "name": "explain_projection",
          "type": "jsonb",
          "primaryKey": false,
          "notNull": true,
          "default": "'{}'::jsonb"
        },
        "created_at": {
          "name": "created_at",
          "type": "timestamp with time zone",
          "primaryKey": false,
          "notNull": true,
          "default": "now()"
        },
        "updated_at": {
          "name": "updated_at",
          "type": "timestamp with time zone",
          "primaryKey": false,
          "notNull": true,
          "default": "now()"
        }
      },
      "indexes": {
        "catalog_index_entries_center_catalog_unique": {
          "name": "catalog_index_entries_center_catalog_unique",
          "columns": [
            {
              "expression": "center_id",
              "isExpression": false,
              "asc": true,
              "nulls": "last"
            },
            {
              "expression": "catalog_id",
              "isExpression": false,
              "asc": true,
              "nulls": "last"
            }
          ],
          "isUnique": true,
          "concurrently": false,
          "method": "btree",
          "with": {}
        },
        "catalog_index_entries_status_idx": {
          "name": "catalog_index_entries_status_idx",
          "columns": [
            {
              "expression": "center_id",
              "isExpression": false,
              "asc": true,
              "nulls": "last"
            },
            {
              "expression": "entry_status",
              "isExpression": false,
              "asc": true,
              "nulls": "last"
            },
            {
              "expression": "verification_status",
              "isExpression": false,
              "asc": true,
              "nulls": "last"
            }
          ],
          "isUnique": false,
          "concurrently": false,
          "method": "btree",
          "with": {}
        }
      },
      "foreignKeys": {},
      "compositePrimaryKeys": {},
      "uniqueConstraints": {},
      "policies": {},
      "checkConstraints": {},
      "isRLSEnabled": false
    },
    "public.catalog_manifest_snapshots": {
      "name": "catalog_manifest_snapshots",
      "schema": "",
      "columns": {
        "id": {
          "name": "id",
          "type": "text",
          "primaryKey": true,
          "notNull": true
        },
        "center_id": {
          "name": "center_id",
          "type": "text",
          "primaryKey": false,
          "notNull": true
        },
        "catalog_id": {
          "name": "catalog_id",
          "type": "text",
          "primaryKey": false,
          "notNull": true
        },
        "registration_id": {
          "name": "registration_id",
          "type": "text",
          "primaryKey": false,
          "notNull": true
        },
        "manifest_url": {
          "name": "manifest_url",
          "type": "text",
          "primaryKey": false,
          "notNull": true
        },
        "discovery_payload": {
          "name": "discovery_payload",
          "type": "jsonb",
          "primaryKey": false,
          "notNull": true
        },
        "manifest_payload": {
          "name": "manifest_payload",
          "type": "jsonb",
          "primaryKey": false,
          "notNull": true
        },
        "manifest_hash": {
          "name": "manifest_hash",
          "type": "text",
          "primaryKey": false,
          "notNull": true
        },
        "supported_object_types": {
          "name": "supported_object_types",
          "type": "jsonb",
          "primaryKey": false,
          "notNull": true,
          "default": "'[]'::jsonb"
        },
        "query_capabilities": {
          "name": "query_capabilities",
          "type": "jsonb",
          "primaryKey": false,
          "notNull": true,
          "default": "'[]'::jsonb"
        },
        "object_contract_summaries": {
          "name": "object_contract_summaries",
          "type": "jsonb",
          "primaryKey": false,
          "notNull": true,
          "default": "'[]'::jsonb"
        },
        "created_at": {
          "name": "created_at",
          "type": "timestamp with time zone",
          "primaryKey": false,
          "notNull": true,
          "default": "now()"
        }
      },
      "indexes": {
        "catalog_manifest_snapshots_catalog_idx": {
          "name": "catalog_manifest_snapshots_catalog_idx",
          "columns": [
            {
              "expression": "center_id",
              "isExpression": false,
              "asc": true,
              "nulls": "last"
            },
            {
              "expression": "catalog_id",
              "isExpression": false,
              "asc": true,
              "nulls": "last"
            },
            {
              "expression": "created_at",
              "isExpression": false,
              "asc": true,
              "nulls": "last"
            }
          ],
          "isUnique": false,
          "concurrently": false,
          "method": "btree",
          "with": {}
        }
      },
      "foreignKeys": {},
      "compositePrimaryKeys": {},
      "uniqueConstraints": {},
      "policies": {},
      "checkConstraints": {},
      "isRLSEnabled": false
    },
    "public.catalog_registration_records": {
      "name": "catalog_registration_records",
      "schema": "",
      "columns": {
        "id": {
          "name": "id",
          "type": "text",
          "primaryKey": true,
          "notNull": true
        },
        "center_id": {
          "name": "center_id",
          "type": "text",
          "primaryKey": false,
          "notNull": true
        },
        "catalog_id": {
          "name": "catalog_id",
          "type": "text",
          "primaryKey": false,
          "notNull": true
        },
        "registration_version": {
          "name": "registration_version",
          "type": "integer",
          "primaryKey": false,
          "notNull": true
        },
        "status": {
          "name": "status",
          "type": "text",
          "primaryKey": false,
          "notNull": true
        },
        "registration_payload": {
          "name": "registration_payload",
          "type": "jsonb",
          "primaryKey": false,
          "notNull": true
        },
        "result_payload": {
          "name": "result_payload",
          "type": "jsonb",
          "primaryKey": false,
          "notNull": false
        },
        "source_ip": {
          "name": "source_ip",
          "type": "text",
          "primaryKey": false,
          "notNull": false
        },
        "user_agent": {
          "name": "user_agent",
          "type": "text",
          "primaryKey": false,
          "notNull": false
        },
        "created_at": {
          "name": "created_at",
          "type": "timestamp with time zone",
          "primaryKey": false,
          "notNull": true,
          "default": "now()"
        }
      },
      "indexes": {
        "catalog_registration_records_version_unique": {
          "name": "catalog_registration_records_version_unique",
          "columns": [
            {
              "expression": "center_id",
              "isExpression": false,
              "asc": true,
              "nulls": "last"
            },
            {
              "expression": "catalog_id",
              "isExpression": false,
              "asc": true,
              "nulls": "last"
            },
            {
              "expression": "registration_version",
              "isExpression": false,
              "asc": true,
              "nulls": "last"
            }
          ],
          "isUnique": true,
          "concurrently": false,
          "method": "btree",
          "with": {}
        },
        "catalog_registration_records_catalog_idx": {
          "name": "catalog_registration_records_catalog_idx",
          "columns": [
            {
              "expression": "center_id",
              "isExpression": false,
              "asc": true,
              "nulls": "last"
            },
            {
              "expression": "catalog_id",
              "isExpression": false,
              "asc": true,
              "nulls": "last"
            }
          ],
          "isUnique": false,
          "concurrently": false,
          "method": "btree",
          "with": {}
        }
      },
      "foreignKeys": {},
      "compositePrimaryKeys": {},
      "uniqueConstraints": {},
      "policies": {},
      "checkConstraints": {},
      "isRLSEnabled": false
    },
    "public.catalog_search_audit_records": {
      "name": "catalog_search_audit_records",
      "schema": "",
      "columns": {
        "id": {
          "name": "id",
          "type": "text",
          "primaryKey": true,
          "notNull": true
        },
        "center_id": {
          "name": "center_id",
          "type": "text",
          "primaryKey": false,
          "notNull": true
        },
        "request_payload": {
          "name": "request_payload",
          "type": "jsonb",
          "primaryKey": false,
          "notNull": true
        },
        "result_count": {
          "name": "result_count",
          "type": "integer",
          "primaryKey": false,
          "notNull": true,
          "default": 0
        },
        "requester_key_hash": {
          "name": "requester_key_hash",
          "type": "text",
          "primaryKey": false,
          "notNull": false
        },
        "created_at": {
          "name": "created_at",
          "type": "timestamp with time zone",
          "primaryKey": false,
          "notNull": true,
          "default": "now()"
        }
      },
      "indexes": {
        "catalog_search_audit_records_center_created_idx": {
          "name": "catalog_search_audit_records_center_created_idx",
          "columns": [
            {
              "expression": "center_id",
              "isExpression": false,
              "asc": true,
              "nulls": "last"
            },
            {
              "expression": "created_at",
              "isExpression": false,
              "asc": true,
              "nulls": "last"
            }
          ],
          "isUnique": false,
          "concurrently": false,
          "method": "btree",
          "with": {}
        }
      },
      "foreignKeys": {},
      "compositePrimaryKeys": {},
      "uniqueConstraints": {},
      "policies": {},
      "checkConstraints": {},
      "isRLSEnabled": false
    },
    "public.catalog_verification_records": {
      "name": "catalog_verification_records",
      "schema": "",
      "columns": {
        "id": {
          "name": "id",
          "type": "text",
          "primaryKey": true,
          "notNull": true
        },
        "center_id": {
          "name": "center_id",
          "type": "text",
          "primaryKey": false,
          "notNull": true
        },
        "catalog_id": {
          "name": "catalog_id",
          "type": "text",
          "primaryKey": false,
          "notNull": true
        },
        "challenge_type": {
          "name": "challenge_type",
          "type": "text",
          "primaryKey": false,
          "notNull": true
        },
        "challenge_payload": {
          "name": "challenge_payload",
          "type": "jsonb",
          "primaryKey": false,
          "notNull": true
        },
        "status": {
          "name": "status",
          "type": "text",
          "primaryKey": false,
          "notNull": true
        },
        "verified_domain": {
          "name": "verified_domain",
          "type": "text",
          "primaryKey": false,
          "notNull": false
        },
        "verified_at": {
          "name": "verified_at",
          "type": "timestamp with time zone",
          "primaryKey": false,
          "notNull": false
        },
        "expires_at": {
          "name": "expires_at",
          "type": "timestamp with time zone",
          "primaryKey": false,
          "notNull": true
        },
        "created_at": {
          "name": "created_at",
          "type": "timestamp with time zone",
          "primaryKey": false,
          "notNull": true,
          "default": "now()"
        }
      },
      "indexes": {
        "catalog_verification_records_catalog_idx": {
          "name": "catalog_verification_records_catalog_idx",
          "columns": [
            {
              "expression": "center_id",
              "isExpression": false,
              "asc": true,
              "nulls": "last"
            },
            {
              "expression": "catalog_id",
              "isExpression": false,
              "asc": true,
              "nulls": "last"
            }
          ],
          "isUnique": false,
          "concurrently": false,
          "method": "btree",
          "with": {}
        }
      },
      "foreignKeys": {},
      "compositePrimaryKeys": {},
      "uniqueConstraints": {},
      "policies": {},
      "checkConstraints": {},
      "isRLSEnabled": false
    },
    "public.registered_catalogs": {
      "name": "registered_catalogs",
      "schema": "",
      "columns": {
        "id": {
          "name": "id",
          "type": "text",
          "primaryKey": true,
          "notNull": true
        },
        "center_id": {
          "name": "center_id",
          "type": "text",
          "primaryKey": false,
          "notNull": true
        },
        "catalog_id": {
          "name": "catalog_id",
          "type": "text",
          "primaryKey": false,
          "notNull": true
        },
        "active_registration_id": {
          "name": "active_registration_id",
          "type": "text",
          "primaryKey": false,
          "notNull": false
        },
        "active_registration_version": {
          "name": "active_registration_version",
          "type": "integer",
          "primaryKey": false,
          "notNull": false
        },
        "active_snapshot_id": {
          "name": "active_snapshot_id",
          "type": "text",
          "primaryKey": false,
          "notNull": false
        },
        "status": {
          "name": "status",
          "type": "text",
          "primaryKey": false,
          "notNull": true,
          "default": "'pending_verification'"
        },
        "verification_status": {
          "name": "verification_status",
          "type": "text",
          "primaryKey": false,
          "notNull": true,
          "default": "'challenge_required'"
        },
        "health_status": {
          "name": "health_status",
          "type": "text",
          "primaryKey": false,
          "notNull": true,
          "default": "'unknown'"
        },
        "trust_tier": {
          "name": "trust_tier",
          "type": "text",
          "primaryKey": false,
          "notNull": true,
          "default": "'unverified'"
        },
        "catalog_access_token_hash": {
          "name": "catalog_access_token_hash",
          "type": "text",
          "primaryKey": false,
          "notNull": false
        },
        "token_issued_at": {
          "name": "token_issued_at",
          "type": "timestamp with time zone",
          "primaryKey": false,
          "notNull": false
        },
        "homepage": {
          "name": "homepage",
          "type": "text",
          "primaryKey": false,
          "notNull": true
        },
        "well_known_url": {
          "name": "well_known_url",
          "type": "text",
          "primaryKey": false,
          "notNull": true
        },
        "claimed_domains": {
          "name": "claimed_domains",
          "type": "jsonb",
          "primaryKey": false,
          "notNull": true,
          "default": "'[]'::jsonb"
        },
        "operator": {
          "name": "operator",
          "type": "jsonb",
          "primaryKey": false,
          "notNull": true,
          "default": "'{}'::jsonb"
        },
        "created_at": {
          "name": "created_at",
          "type": "timestamp with time zone",
          "primaryKey": false,
          "notNull": true,
          "default": "now()"
        },
        "updated_at": {
          "name": "updated_at",
          "type": "timestamp with time zone",
          "primaryKey": false,
          "notNull": true,
          "default": "now()"
        }
      },
      "indexes": {
        "registered_catalogs_center_catalog_unique": {
          "name": "registered_catalogs_center_catalog_unique",
          "columns": [
            {
              "expression": "center_id",
              "isExpression": false,
              "asc": true,
              "nulls": "last"
            },
            {
              "expression": "catalog_id",
              "isExpression": false,
              "asc": true,
              "nulls": "last"
            }
          ],
          "isUnique": true,
          "concurrently": false,
          "method": "btree",
          "with": {}
        },
        "registered_catalogs_status_idx": {
          "name": "registered_catalogs_status_idx",
          "columns": [
            {
              "expression": "center_id",
              "isExpression": false,
              "asc": true,
              "nulls": "last"
            },
            {
              "expression": "status",
              "isExpression": false,
              "asc": true,
              "nulls": "last"
            },
            {
              "expression": "verification_status",
              "isExpression": false,
              "asc": true,
              "nulls": "last"
            }
          ],
          "isUnique": false,
          "concurrently": false,
          "method": "btree",
          "with": {}
        }
      },
      "foreignKeys": {},
      "compositePrimaryKeys": {},
      "uniqueConstraints": {},
      "policies": {},
      "checkConstraints": {},
      "isRLSEnabled": false
    }
  },
  "enums": {
    "public.catalog_search_document_status": {
      "name": "catalog_search_document_status",
      "schema": "public",
      "values": [
        "pending",
        "active",
        "inactive",
        "stale",
        "failed"
      ]
    },
    "public.catalog_search_index_job_status": {
      "name": "catalog_search_index_job_status",
      "schema": "public",
      "values": [
        "pending",
        "running",
        "completed",
        "failed",
        "cancelled"
      ]
    },
    "public.catalog_search_index_job_type": {
      "name": "catalog_search_index_job_type",
      "schema": "public",
      "values": [
        "upsert_document",
        "rebuild_document",
        "delete_document",
        "refresh_embedding",
        "rebuild_all_for_provider"
      ]
    },
    "public.entry_status": {
      "name": "entry_status",
      "schema": "public",
      "values": [
        "active",
        "inactive",
        "rejected",
        "pending_verification"
      ]
    },
    "public.object_sync_batch_status": {
      "name": "object_sync_batch_status",
      "schema": "public",
      "values": [
        "accepted",
        "partial",
        "rejected"
      ]
    },
    "public.object_sync_item_status": {
      "name": "object_sync_item_status",
      "schema": "public",
      "values": [
        "accepted",
        "rejected"
      ]
    },
    "public.provider_contract_state_status": {
      "name": "provider_contract_state_status",
      "schema": "public",
      "values": [
        "active",
        "inactive",
        "rejected"
      ]
    },
    "public.registration_status": {
      "name": "registration_status",
      "schema": "public",
      "values": [
        "accepted_full",
        "accepted_limited",
        "rejected",
        "pending_verification"
      ]
    }
  },
  "schemas": {},
  "sequences": {},
  "roles": {},
  "policies": {},
  "views": {},
  "_meta": {
    "columns": {},
    "schemas": {},
    "tables": {}
  }
}